odoo9_addon_sale_delivery_block-9.0.1.0.0-py2.7-nspkg.pth
odoo9_addon_sale_delivery_block-9.0.1.0.0.dist-info/DESCRIPTION.rst
odoo9_addon_sale_delivery_block-9.0.1.0.0.dist-info/METADATA
odoo9_addon_sale_delivery_block-9.0.1.0.0.dist-info/RECORD
odoo9_addon_sale_delivery_block-9.0.1.0.0.dist-info/WHEEL
odoo9_addon_sale_delivery_block-9.0.1.0.0.dist-info/metadata.json
odoo9_addon_sale_delivery_block-9.0.1.0.0.dist-info/namespace_packages.txt
odoo9_addon_sale_delivery_block-9.0.1.0.0.dist-info/top_level.txt
odoo_addons/sale_delivery_block/README.rst
odoo_addons/sale_delivery_block/__init__.py
odoo_addons/sale_delivery_block/__openerp__.py
odoo_addons/sale_delivery_block/data/sale_delivery_block_reason_data.xml
odoo_addons/sale_delivery_block/models/__init__.py
odoo_addons/sale_delivery_block/models/res_partner.py
odoo_addons/sale_delivery_block/models/sale_delivery_block_reason.py
odoo_addons/sale_delivery_block/models/sale_order.py
odoo_addons/sale_delivery_block/security/ir.model.access.csv
odoo_addons/sale_delivery_block/security/sale_delivery_block_security.xml
odoo_addons/sale_delivery_block/tests/__init__.py
odoo_addons/sale_delivery_block/tests/test_sale_delivery_block.py
odoo_addons/sale_delivery_block/views/res_partner_view.xml
odoo_addons/sale_delivery_block/views/sale_delivery_block_reason_view.xml
odoo_addons/sale_delivery_block/views/sale_order_view.xml
